js_host
tests
example
