Metadata-Version: 1.0
Name: js-host
Version: 0.2.0
Summary: Python bindings to a performant JavaScript environment
Home-page: https://github.com/markfinger/python-js-host
Author: Mark Finger
Author-email: markfinger@gmail.com
License: UNKNOWN
Platform: UNKNOWN
